flamapy/metamodels/fm_metamodel/__init__.py
flamapy/metamodels/fm_metamodel/models/__init__.py
flamapy/metamodels/fm_metamodel/models/feature_model.py
flamapy/metamodels/fm_metamodel/operations/__init__.py
flamapy/metamodels/fm_metamodel/operations/fm_atomic_sets.py
flamapy/metamodels/fm_metamodel/operations/fm_average_branching_factor.py
flamapy/metamodels/fm_metamodel/operations/fm_core_features.py
flamapy/metamodels/fm_metamodel/operations/fm_count_leafs.py
flamapy/metamodels/fm_metamodel/operations/fm_estimated_configurations_number.py
flamapy/metamodels/fm_metamodel/operations/fm_feature_ancestors.py
flamapy/metamodels/fm_metamodel/operations/fm_generate_random_attribute.py
flamapy/metamodels/fm_metamodel/operations/fm_leaf_features.py
flamapy/metamodels/fm_metamodel/operations/fm_max_depth_tree.py
flamapy/metamodels/fm_metamodel/operations/fm_metrics.py
flamapy/metamodels/fm_metamodel/operations/fm_variation_points.py
flamapy/metamodels/fm_metamodel/operations/interfaces/__init__.py
flamapy/metamodels/fm_metamodel/operations/interfaces/variation_points.py
flamapy/metamodels/fm_metamodel/transformations/__init__.py
flamapy/metamodels/fm_metamodel/transformations/afm_reader.py
flamapy/metamodels/fm_metamodel/transformations/afm_writer.py
flamapy/metamodels/fm_metamodel/transformations/clafer_writer.py
flamapy/metamodels/fm_metamodel/transformations/featureide_reader.py
flamapy/metamodels/fm_metamodel/transformations/featureide_writer.py
flamapy/metamodels/fm_metamodel/transformations/glencoe_reader.py
flamapy/metamodels/fm_metamodel/transformations/glencoe_writer.py
flamapy/metamodels/fm_metamodel/transformations/json_reader.py
flamapy/metamodels/fm_metamodel/transformations/json_writer.py
flamapy/metamodels/fm_metamodel/transformations/pysat_to_fm.py
flamapy/metamodels/fm_metamodel/transformations/splot_writer.py
flamapy/metamodels/fm_metamodel/transformations/uvl_reader.py
flamapy/metamodels/fm_metamodel/transformations/uvl_writer.py
flamapy_fm-2.0.1.dist-info/METADATA
flamapy_fm-2.0.1.dist-info/WHEEL
flamapy_fm-2.0.1.dist-info/top_level.txt
flamapy_fm-2.0.1.dist-info/RECORD
